bitget/__init__.py
bitget/ccxt/__init__.py
bitget/ccxt/bitget.py
bitget/ccxt/abstract/bitget.py
bitget/ccxt/async_support/__init__.py
bitget/ccxt/async_support/bitget.py
bitget/ccxt/async_support/base/__init__.py
bitget/ccxt/async_support/base/exchange.py
bitget/ccxt/async_support/base/throttler.py
bitget/ccxt/async_support/base/ws/__init__.py
bitget/ccxt/async_support/base/ws/cache.py
bitget/ccxt/async_support/base/ws/client.py
bitget/ccxt/async_support/base/ws/functions.py
bitget/ccxt/async_support/base/ws/future.py
bitget/ccxt/async_support/base/ws/order_book.py
bitget/ccxt/async_support/base/ws/order_book_side.py
bitget/ccxt/base/__init__.py
bitget/ccxt/base/decimal_to_precision.py
bitget/ccxt/base/errors.py
bitget/ccxt/base/exchange.py
bitget/ccxt/base/precise.py
bitget/ccxt/base/types.py
bitget/ccxt/pro/__init__.py
bitget/ccxt/pro/bitget.py
bitget/ccxt/static_dependencies/README.md
bitget/ccxt/static_dependencies/__init__.py
bitget/ccxt/static_dependencies/bip/__init__.py
bitget/ccxt/static_dependencies/bip/addr/P2PKH_addr.py
bitget/ccxt/static_dependencies/bip/addr/__init__.py
bitget/ccxt/static_dependencies/bip/addr/addr_dec_utils.py
bitget/ccxt/static_dependencies/bip/addr/addr_key_validator.py
bitget/ccxt/static_dependencies/bip/addr/iaddr_decoder.py
bitget/ccxt/static_dependencies/bip/addr/iaddr_encoder.py
bitget/ccxt/static_dependencies/bip/base58/__init__.py
bitget/ccxt/static_dependencies/bip/base58/base58.py
bitget/ccxt/static_dependencies/bip/base58/base58_ex.py
bitget/ccxt/static_dependencies/bip/base58/base58_xmr.py
bitget/ccxt/static_dependencies/bip/bech32/__init__.py
bitget/ccxt/static_dependencies/bip/bech32/bch_bech32.py
bitget/ccxt/static_dependencies/bip/bech32/bech32.py
bitget/ccxt/static_dependencies/bip/bech32/bech32_base.py
bitget/ccxt/static_dependencies/bip/bech32/bech32_ex.py
bitget/ccxt/static_dependencies/bip/bech32/segwit_bech32.py
bitget/ccxt/static_dependencies/bip/bip32/__init__.py
bitget-0.0.120.dist-info/METADATA
bitget-0.0.120.dist-info/WHEEL
bitget-0.0.120.dist-info/RECORD
