Metadata-Version: 2.4
Name: bitget
Version: 0.0.120
Summary: bitget crypto exchange api client
Project-URL: Homepage, https://github.com/ccxt/ccxt
Project-URL: Issues, https://github.com/ccxt/ccxt
Author-email: CCXT <info@ccxt.trade>
License: MIT
Classifier: Intended Audience :: Developers
Classifier: Intended Audience :: Financial and Insurance Industry
Classifier: Intended Audience :: Information Technology
Classifier: License :: OSI Approved :: MIT License
Classifier: Operating System :: OS Independent
Classifier: Programming Language :: Python :: 3
Classifier: Topic :: Office/Business :: Financial :: Investment
Classifier: Topic :: Software Development :: Build Tools
Requires-Python: >=3.8
